./.gitignore
./PKG-INFO
./README.md
./__init__.py
./detect_lewd_images.py
./pyproject.toml
./test.py
feluda_detect_lewd_image-0.2.0.dist-info/METADATA
feluda_detect_lewd_image-0.2.0.dist-info/WHEEL
feluda_detect_lewd_image-0.2.0.dist-info/RECORD
