Metadata-Version: 2.4
Name: feluda-detect-lewd-image
Version: 0.2.0
Requires-Python: >=3.10
Requires-Dist: huggingface-hub>=0.30.2
Requires-Dist: tensorflow>=2.19.0
